Workbook

Sheet README
A1: DecodeLabs – Project 2: Exploratory Data Analysis (EDA)
A3: Project Goal | B3: Analyze a sales dataset to understand patterns, trends, distributions, outliers and relationships.
A4: Dataset | B4: 120 synthetic retail orders across 6 different Indian cities, 3 different categories and 12 months. Unit_Price is included so Sales can be independently calculated.
A5: Basic Statistics | B5: Count, Mean, Median, Minimum, Maximum and Standard Deviation are provided in the Basic Statistics sheet.
A6: Outlier Method | B6: Sales = Unit_Price × Quantity × (1 − Discount%/100). Profit = Sales × Profit_Margin.
A7: Trend Analysis | B7: Monthly, category-wise and city-wise sales/profit summaries are included with charts. Categories, cities and products are distinct from the original project dataset.
A8: Correlation | B8: Pearson correlation is calculated for numeric variables.
A9: Key Insights | B9: Main observations and actionable recommendations are summarized in Insights & Recommendations.
A10: Important Note | B10: Potential outliers are flagged for investigation; they are not automatically deleted.
A11: Project Alignment | B11: The workbook covers the PDF's mandatory EDA requirements: basic statistics, trends/outliers, and key observations.
A13: Formula note: | B13: Calculated sheets use Excel formulas so selecting a result cell shows the formula in the formula bar.

Sheet Dataset
A1: Order_Date | B1: City | C1: Category | D1: Product | E1: Unit_Price | F1: Quantity | G1: Discount_% | H1: Sales | I1: Profit | J1: Profit_Margin | K1: Customer_Rating
A2: ORD-2001 | B2: 45658 | C2: Jaipur | D2: Home Decor | E2: Cushion Set | F2: 1440.42 | G2: 6 | H2: 10 | I2: =ROUND(F2*G2*(1-H2/100),2) -> 7778.27 | J2: =ROUND(I2*K2,2) -> 1815.45 | K2: 0.2334 | L2: 4.8
A3: ORD-2002 | B3: 45690 | C3: Lucknow | D3: Home Decor | E3: Wall Clock | F3: 4790.01 | G3: 7 | H3: 10 | I3: =ROUND(F3*G3*(1-H3/100),2) -> 30177.06 | J3: =ROUND(I3*K3,2) -> 6744.57 | K3: 0.2235 | L3: 4.8
A4: ORD-2003 | B4: 45719 | C4: Nagpur | D4: Sports & Fitness | E4: Resistance Band | F4: 1246.78 | G4: 5 | H4: 0 | I4: =ROUND(F4*G4*(1-H4/100),2) -> 6233.9 | J4: =ROUND(I4*K4,2) -> 1024.23 | K4: 0.1643 | L4: 4.2
A5: ORD-2004 | B5: 45751 | C5: Nagpur | D5: Sports & Fitness | E5: Fitness Ball | F5: 6459.84 | G5: 10 | H5: 5 | I5: =ROUND(F5*G5*(1-H5/100),2) -> 61368.48 | J5: =ROUND(I5*K5,2) -> 12813.74 | K5: 0.2088 | L5: 4.7
A6: ORD-2005 | B6: 45782 | C6: Jaipur | D6: Sports & Fitness | E6: Resistance Band | F6: 711.97 | G6: 5 | H6: 15 | I6: =ROUND(F6*G6*(1-H6/100),2) -> 3025.87 | J6: =ROUND(I6*K6,2) -> 494.73 | K6: 0.1635 | L6: 4.2
A7: ORD-2006 | B7: 45814 | C7: Lucknow | D7: Grocery | E7: Dry Fruits | F7: 3024.7 | G7: 8 | H7: 5 | I7: =ROUND(F7*G7*(1-H7/100),2) -> 22987.72 | J7: =ROUND(I7*K7,2) -> 6820.46 | K7: 0.2967 | L7: 4.8
A8: ORD-2007 | B8: 45845 | C8: Kochi | D8: Grocery | E8: Breakfast Cereal | F8: 242.82 | G8: 7 | H8: 5 | I8: =ROUND(F8*G8*(1-H8/100),2) -> 1614.75 | J8: =ROUND(I8*K8,2) -> 442.76 | K8: 0.2742 | L8: 4.9
A9: ORD-2008 | B9: 45877 | C9: Vadodara | D9: Sports & Fitness | E9: Yoga Mat | F9: 5383.86 | G9: 9 | H9: 5 | I9: =ROUND(F9*G9*(1-H9/100),2) -> 46032 | J9: =ROUND(I9*K9,2) -> 8534.33 | K9: 0.1854 | L9: 3.9
A10: ORD-2009 | B10: 45909 | C10: Vadodara | D10: Home Decor | E10: Wall Clock | F10: 5304.62 | G10: 5 | H10: 10 | I10: =ROUND(F10*G10*(1-H10/100),2) -> 23870.79 | J10: =ROUND(I10*K10,2) -> 3482.75 | K10: 0.1459 | L10: 4
A11: ORD-2010 | B11: 45940 | C11: Jaipur | D11: Home Decor | E11: Cushion Set | F11: 4274.28 | G11: 9 | H11: 15 | I11: =ROUND(F11*G11*(1-H11/100),2) -> 32698.24 | J11: =ROUND(I11*K11,2) -> 8723.89 | K11: 0.2668 | L11: 4
A12: ORD-2011 | B12: 45972 | C12: Indore | D12: Sports & Fitness | E12: Dumbbell Set | F12: 694.14 | G12: 9 | H12: 0 | I12: =ROUND(F12*G12*(1-H12/100),2) -> 6247.26 | J12: =ROUND(I12*K12,2) -> 786.53 | K12: 0.1259 | L12: 4.1
A13: ORD-2012 | B13: 46003 | C13: Kochi | D13: Grocery | E13: Breakfast Cereal | F13: 773.77 | G13: 6 | H13: 15 | I13: =ROUND(F13*G13*(1-H13/100),2) -> 3946.23 | J13: =ROUND(I13*K13,2) -> 630.61 | K13: 0.1598 | L13: 4.3
... A121: ORD-2120 | B121: 46003 | C121: Jaipur | D121: Home Decor | E121: Wall Clock | F121: 2884.26 | G121: 2 | H121: 10 | I121: =ROUND(F121*G121*(1-H121/100),2) -> 5191.67 | J121: =ROUND(I121*K121,2) -> 674.4 | K121: 0.1299 | L121: 4.2

Sheet Basic Statistics
A1: Metric | B1: Count | C1: Mean | D1: Median | E1: Minimum | F1: Maximum | G1: Std_Dev
A2: Quantity | B2: =COUNT(Dataset!G2:G121) -> 120 | C2: =AVERAGE(Dataset!G2:G121) -> 5.7166667 | D2: =MEDIAN(Dataset!G2:G121) -> 6 | E2: =MIN(Dataset!G2:G121) -> 1 | F2: =MAX(Dataset!G2:G121) -> 10 | G2: =STDEV(Dataset!G2:G121) -> 3.0546378
A3: Discount_% | B3: =COUNT(Dataset!H2:H121) -> 120 | C3: =AVERAGE(Dataset!H2:H121) -> 7.4166667 | D3: =MEDIAN(Dataset!H2:H121) -> 5 | E3: =MIN(Dataset!H2:H121) -> 0 | F3: =MAX(Dataset!H2:H121) -> 15 | G3: =STDEV(Dataset!H2:H121) -> 5.4995543
A4: Sales | B4: =COUNT(Dataset!I2:I121) -> 120 | C4: =AVERAGE(Dataset!I2:I121) -> 17590.528 | D4: =MEDIAN(Dataset!I2:I121) -> 10178.505 | E4: =MIN(Dataset!I2:I121) -> 465.35 | F4: =MAX(Dataset!I2:I121) -> 61368.48 | G4: =STDEV(Dataset!I2:I121) -> 17091.955
A5: Profit | B5: =COUNT(Dataset!J2:J121) -> 120 | C5: =AVERAGE(Dataset!J2:J121) -> 3868.3498 | D5: =MEDIAN(Dataset!J2:J121) -> 2140.915 | E5: =MIN(Dataset!J2:J121) -> 86.13 | F5: =MAX(Dataset!J2:J121) -> 16847.9 | G5: =STDEV(Dataset!J2:J121) -> 4053.808
A6: Customer_Rating | B6: =COUNT(Dataset!L2:L121) -> 120 | C6: =AVERAGE(Dataset!L2:L121) -> 4.3625 | D6: =MEDIAN(Dataset!L2:L121) -> 4.4 | E6: =MIN(Dataset!L2:L121) -> 3.6 | F6: =MAX(Dataset!L2:L121) -> 5 | G6: =STDEV(Dataset!L2:L121) -> 0.3906604

Sheet Outlier Summary
A1: Variable | B1: Q1 | C1: Q3 | D1: IQR | E1: Lower_Bound | F1: Upper_Bound | G1: Outlier_Count
A2: Sales | B2: =QUARTILE(Dataset!I2:I121,1) -> 3610.3175 | C2: =QUARTILE(Dataset!I2:I121,3) -> 30286.658 | D2: =C2-B2 -> 26676.34 | E2: =B2-(1.5*D2) -> -36404.193 | F2: =C2+(1.5*D2) -> 70301.168 | G2: =COUNTIF(Dataset!I2:I121,">"&F2)+COUNTIF(Dataset!I2:I121,"<"&E2) -> 0
A3: Profit | B3: =QUARTILE(Dataset!J2:J121,1) -> 743.4675 | C3: =QUARTILE(Dataset!J2:J121,3) -> 6367.8 | D3: =C3-B3 -> 5624.3325 | E3: =B3-(1.5*D3) -> -7693.0313 | F3: =C3+(1.5*D3) -> 14804.299 | G3: =COUNTIF(Dataset!J2:J121,">"&F3)+COUNTIF(Dataset!J2:J121,"<"&E3) -> 2

Sheet Outliers
A1: Order_ID | B1: Variable | C1: Value | D1: Reason
A2: ORD-2017 | B2: Profit | C2: 15821.26 | D2: Above upper limit
A3: ORD-2117 | B3: Profit | C3: 16847.9 | D3: Above upper limit

Sheet Monthly Trend
A1: Month | B1: Total_Sales | C1: Total_Profit | D1: Orders
A2: Jan | B2: =SUMIFS(Dataset!$I$2:$I$121,Dataset!$B$2:$B$121,">="&DATE(2025,1,1),Dataset!$B$2:$B$121,"<"&EDATE(DATE(2025,1,1),1)) -> 112703.29 | C2: =SUMIFS(Dataset!$J$2:$J$121,Dataset!$B$2:$B$121,">="&DATE(2025,1,1),Dataset!$B$2:$B$121,"<"&EDATE(DATE(2025,1,1),1)) -> 22007.77 | D2: =COUNTIFS(Dataset!$B$2:$B$121,">="&DATE(2025,1,1),Dataset!$B$2:$B$121,"<"&EDATE(DATE(2025,1,1),1)) -> 10
A3: Feb | B3: =SUMIFS(Dataset!$I$2:$I$121,Dataset!$B$2:$B$121,">="&DATE(2025,2,1),Dataset!$B$2:$B$121,"<"&EDATE(DATE(2025,2,1),1)) -> 102841.87 | C3: =SUMIFS(Dataset!$J$2:$J$121,Dataset!$B$2:$B$121,">="&DATE(2025,2,1),Dataset!$B$2:$B$121,"<"&EDATE(DATE(2025,2,1),1)) -> 23842.45 | D3: =COUNTIFS(Dataset!$B$2:$B$121,">="&DATE(2025,2,1),Dataset!$B$2:$B$121,"<"&EDATE(DATE(2025,2,1),1)) -> 10
A4: Mar | B4: =SUMIFS(Dataset!$I$2:$I$121,Dataset!$B$2:$B$121,">="&DATE(2025,3,1),Dataset!$B$2:$B$121,"<"&EDATE(DATE(2025,3,1),1)) -> 169393.91 | C4: =SUMIFS(Dataset!$J$2:$J$121,Dataset!$B$2:$B$121,">="&DATE(2025,3,1),Dataset!$B$2:$B$121,"<"&EDATE(DATE(2025,3,1),1)) -> 30751.86 | D4: =COUNTIFS(Dataset!$B$2:$B$121,">="&DATE(2025,3,1),Dataset!$B$2:$B$121,"<"&EDATE(DATE(2025,3,1),1)) -> 10
A5: Apr | B5: =SUMIFS(Dataset!$I$2:$I$121,Dataset!$B$2:$B$121,">="&DATE(2025,4,1),Dataset!$B$2:$B$121,"<"&EDATE(DATE(2025,4,1),1)) -> 184867.89 | C5: =SUMIFS(Dataset!$J$2:$J$121,Dataset!$B$2:$B$121,">="&DATE(2025,4,1),Dataset!$B$2:$B$121,"<"&EDATE(DATE(2025,4,1),1)) -> 40249.2 | D5: =COUNTIFS(Dataset!$B$2:$B$121,">="&DATE(2025,4,1),Dataset!$B$2:$B$121,"<"&EDATE(DATE(2025,4,1),1)) -> 10
A6: May | B6: =SUMIFS(Dataset!$I$2:$I$121,Dataset!$B$2:$B$121,">="&DATE(2025,5,1),Dataset!$B$2:$B$121,"<"&EDATE(DATE(2025,5,1),1)) -> 236490.89 | C6: =SUMIFS(Dataset!$J$2:$J$121,Dataset!$B$2:$B$121,">="&DATE(2025,5,1),Dataset!$B$2:$B$121,"<"&EDATE(DATE(2025,5,1),1)) -> 54576.78 | D6: =COUNTIFS(Dataset!$B$2:$B$121,">="&DATE(2025,5,1),Dataset!$B$2:$B$121,"<"&EDATE(DATE(2025,5,1),1)) -> 10
A7: Jun | B7: =SUMIFS(Dataset!$I$2:$I$121,Dataset!$B$2:$B$121,">="&DATE(2025,6,1),Dataset!$B$2:$B$121,"<"&EDATE(DATE(2025,6,1),1)) -> 62313.47 | C7: =SUMIFS(Dataset!$J$2:$J$121,Dataset!$B$2:$B$121,">="&DATE(2025,6,1),Dataset!$B$2:$B$121,"<"&EDATE(DATE(2025,6,1),1)) -> 17457.27 | D7: =COUNTIFS(Dataset!$B$2:$B$121,">="&DATE(2025,6,1),Dataset!$B$2:$B$121,"<"&EDATE(DATE(2025,6,1),1)) -> 10
A8: Jul | B8: =SUMIFS(Dataset!$I$2:$I$121,Dataset!$B$2:$B$121,">="&DATE(2025,7,1),Dataset!$B$2:$B$121,"<"&EDATE(DATE(2025,7,1),1)) -> 134879.76 | C8: =SUMIFS(Dataset!$J$2:$J$121,Dataset!$B$2:$B$121,">="&DATE(2025,7,1),Dataset!$B$2:$B$121,"<"&EDATE(DATE(2025,7,1),1)) -> 23673.35 | D8: =COUNTIFS(Dataset!$B$2:$B$121,">="&DATE(2025,7,1),Dataset!$B$2:$B$121,"<"&EDATE(DATE(2025,7,1),1)) -> 10
A9: Aug | B9: =SUMIFS(Dataset!$I$2:$I$121,Dataset!$B$2:$B$121,">="&DATE(2025,8,1),Dataset!$B$2:$B$121,"<"&EDATE(DATE(2025,8,1),1)) -> 278884.46 | C9: =SUMIFS(Dataset!$J$2:$J$121,Dataset!$B$2:$B$121,">="&DATE(2025,8,1),Dataset!$B$2:$B$121,"<"&EDATE(DATE(2025,8,1),1)) -> 64398.73 | D9: =COUNTIFS(Dataset!$B$2:$B$121,">="&DATE(2025,8,1),Dataset!$B$2:$B$121,"<"&EDATE(DATE(2025,8,1),1)) -> 10
A10: Sep | B10: =SUMIFS(Dataset!$I$2:$I$121,Dataset!$B$2:$B$121,">="&DATE(2025,9,1),Dataset!$B$2:$B$121,"<"&EDATE(DATE(2025,9,1),1)) -> 215608.98 | C10: =SUMIFS(Dataset!$J$2:$J$121,Dataset!$B$2:$B$121,">="&DATE(2025,9,1),Dataset!$B$2:$B$121,"<"&EDATE(DATE(2025,9,1),1)) -> 58346.69 | D10: =COUNTIFS(Dataset!$B$2:$B$121,">="&DATE(2025,9,1),Dataset!$B$2:$B$121,"<"&EDATE(DATE(2025,9,1),1)) -> 10
A11: Oct | B11: =SUMIFS(Dataset!$I$2:$I$121,Dataset!$B$2:$B$121,">="&DATE(2025,10,1),Dataset!$B$2:$B$121,"<"&EDATE(DATE(2025,10,1),1)) -> 190640.23 | C11: =SUMIFS(Dataset!$J$2:$J$121,Dataset!$B$2:$B$121,">="&DATE(2025,10,1),Dataset!$B$2:$B$121,"<"&EDATE(DATE(2025,10,1),1)) -> 48642.86 | D11: =COUNTIFS(Dataset!$B$2:$B$121,">="&DATE(2025,10,1),Dataset!$B$2:$B$121,"<"&EDATE(DATE(2025,10,1),1)) -> 10
A12: Nov | B12: =SUMIFS(Dataset!$I$2:$I$121,Dataset!$B$2:$B$121,">="&DATE(2025,11,1),Dataset!$B$2:$B$121,"<"&EDATE(DATE(2025,11,1),1)) -> 202287.55 | C12: =SUMIFS(Dataset!$J$2:$J$121,Dataset!$B$2:$B$121,">="&DATE(2025,11,1),Dataset!$B$2:$B$121,"<"&EDATE(DATE(2025,11,1),1)) -> 32715.07 | D12: =COUNTIFS(Dataset!$B$2:$B$121,">="&DATE(2025,11,1),Dataset!$B$2:$B$121,"<"&EDATE(DATE(2025,11,1),1)) -> 10
A13: Dec | B13: =SUMIFS(Dataset!$I$2:$I$121,Dataset!$B$2:$B$121,">="&DATE(2025,12,1),Dataset!$B$2:$B$121,"<"&EDATE(DATE(2025,12,1),1)) -> 219951.03 | C13: =SUMIFS(Dataset!$J$2:$J$121,Dataset!$B$2:$B$121,">="&DATE(2025,12,1),Dataset!$B$2:$B$121,"<"&EDATE(DATE(2025,12,1),1)) -> 47539.95 | D13: =COUNTIFS(Dataset!$B$2:$B$121,">="&DATE(2025,12,1),Dataset!$B$2:$B$121,"<"&EDATE(DATE(2025,12,1),1)) -> 10

Sheet Category Analysis
A1: Category | B1: Orders | C1: Total_Sales | D1: Total_Profit | E1: Avg_Sales | F1: Avg_Rating
A2: Home Decor | B2: =COUNTIF(Dataset!$D$2:$D$121,A2) -> 43 | C2: =SUMIF(Dataset!$D$2:$D$121,A2,Dataset!$I$2:$I$121) -> 922403.2 | D2: =SUMIF(Dataset!$D$2:$D$121,A2,Dataset!$J$2:$J$121) -> 196405.8 | E2: =AVERAGEIF(Dataset!$D$2:$D$121,A2,Dataset!$I$2:$I$121) -> 21451.237 | F2: =AVERAGEIF(Dataset!$D$2:$D$121,A2,Dataset!$L$2:$L$121) -> 4.3674419
A3: Sports & Fitness | B3: =COUNTIF(Dataset!$D$2:$D$121,A3) -> 47 | C3: =SUMIF(Dataset!$D$2:$D$121,A3,Dataset!$I$2:$I$121) -> 988916.48 | D3: =SUMIF(Dataset!$D$2:$D$121,A3,Dataset!$J$2:$J$121) -> 223693.08 | E3: =AVERAGEIF(Dataset!$D$2:$D$121,A3,Dataset!$I$2:$I$121) -> 21040.776 | F3: =AVERAGEIF(Dataset!$D$2:$D$121,A3,Dataset!$L$2:$L$121) -> 4.312766
A4: Grocery | B4: =COUNTIF(Dataset!$D$2:$D$121,A4) -> 30 | C4: =SUMIF(Dataset!$D$2:$D$121,A4,Dataset!$I$2:$I$121) -> 199543.65 | D4: =SUMIF(Dataset!$D$2:$D$121,A4,Dataset!$J$2:$J$121) -> 44103.1 | E4: =AVERAGEIF(Dataset!$D$2:$D$121,A4,Dataset!$I$2:$I$121) -> 6651.455 | F4: =AVERAGEIF(Dataset!$D$2:$D$121,A4,Dataset!$L$2:$L$121) -> 4.4333333

Sheet City Analysis
A1: City | B1: Orders | C1: Total_Sales | D1: Total_Profit
A2: Jaipur | B2: =COUNTIF(Dataset!$C$2:$C$121,A2) -> 18 | C2: =SUMIF(Dataset!$C$2:$C$121,A2,Dataset!$I$2:$I$121) -> 309872.95 | D2: =SUMIF(Dataset!$C$2:$C$121,A2,Dataset!$J$2:$J$121) -> 66105.89
A3: Lucknow | B3: =COUNTIF(Dataset!$C$2:$C$121,A3) -> 15 | C3: =SUMIF(Dataset!$C$2:$C$121,A3,Dataset!$I$2:$I$121) -> 350945.17 | D3: =SUMIF(Dataset!$C$2:$C$121,A3,Dataset!$J$2:$J$121) -> 73013.91
A4: Kochi | B4: =COUNTIF(Dataset!$C$2:$C$121,A4) -> 27 | C4: =SUMIF(Dataset!$C$2:$C$121,A4,Dataset!$I$2:$I$121) -> 351543.08 | D4: =SUMIF(Dataset!$C$2:$C$121,A4,Dataset!$J$2:$J$121) -> 77787.58
A5: Indore | B5: =COUNTIF(Dataset!$C$2:$C$121,A5) -> 21 | C5: =SUMIF(Dataset!$C$2:$C$121,A5,Dataset!$I$2:$I$121) -> 210841.26 | D5: =SUMIF(Dataset!$C$2:$C$121,A5,Dataset!$J$2:$J$121) -> 46065.29
A6: Nagpur | B6: =COUNTIF(Dataset!$C$2:$C$121,A6) -> 15 | C6: =SUMIF(Dataset!$C$2:$C$121,A6,Dataset!$I$2:$I$121) -> 321216.55 | D6: =SUMIF(Dataset!$C$2:$C$121,A6,Dataset!$J$2:$J$121) -> 73080.29
A7: Vadodara | B7: =COUNTIF(Dataset!$C$2:$C$121,A7) -> 24 | C7: =SUMIF(Dataset!$C$2:$C$121,A7,Dataset!$I$2:$I$121) -> 566444.32 | D7: =SUMIF(Dataset!$C$2:$C$121,A7,Dataset!$J$2:$J$121) -> 128149.02

Sheet Correlation
B1: Quantity | C1: Discount_% | D1: Sales | E1: Profit | F1: Customer_Rating
A2: Quantity | B2: =CORREL(Dataset!$G$2:$G$121,Dataset!$G$2:$G$121) -> 1 | C2: =CORREL(Dataset!$G$2:$G$121,Dataset!$H$2:$H$121) -> -0.1289748 | D2: =CORREL(Dataset!$G$2:$G$121,Dataset!$I$2:$I$121) -> 0.66081415 | E2: =CORREL(Dataset!$G$2:$G$121,Dataset!$J$2:$J$121) -> 0.60384826 | F2: =CORREL(Dataset!$G$2:$G$121,Dataset!$L$2:$L$121) -> 0.019893554
A3: Discount_% | B3: =CORREL(Dataset!$H$2:$H$121,Dataset!$G$2:$G$121) -> -0.1289748 | C3: =CORREL(Dataset!$H$2:$H$121,Dataset!$H$2:$H$121) -> 1 | D3: =CORREL(Dataset!$H$2:$H$121,Dataset!$I$2:$I$121) -> -0.27092209 | E3: =CORREL(Dataset!$H$2:$H$121,Dataset!$J$2:$J$121) -> -0.26736224 | F3: =CORREL(Dataset!$H$2:$H$121,Dataset!$L$2:$L$121) -> 0.054269915
A4: Sales | B4: =CORREL(Dataset!$I$2:$I$121,Dataset!$G$2:$G$121) -> 0.66081415 | C4: =CORREL(Dataset!$I$2:$I$121,Dataset!$H$2:$H$121) -> -0.27092209 | D4: =CORREL(Dataset!$I$2:$I$121,Dataset!$I$2:$I$121) -> 1 | E4: =CORREL(Dataset!$I$2:$I$121,Dataset!$J$2:$J$121) -> 0.93111677 | F4: =CORREL(Dataset!$I$2:$I$121,Dataset!$L$2:$L$121) -> -0.076226371
A5: Profit | B5: =CORREL(Dataset!$J$2:$J$121,Dataset!$G$2:$G$121) -> 0.60384826 | C5: =CORREL(Dataset!$J$2:$J$121,Dataset!$H$2:$H$121) -> -0.26736224 | D5: =CORREL(Dataset!$J$2:$J$121,Dataset!$I$2:$I$121) -> 0.93111677 | E5: =CORREL(Dataset!$J$2:$J$121,Dataset!$J$2:$J$121) -> 1 | F5: =CORREL(Dataset!$J$2:$J$121,Dataset!$L$2:$L$121) -> -0.053494943
A6: Customer_Rating | B6: =CORREL(Dataset!$L$2:$L$121,Dataset!$G$2:$G$121) -> 0.019893554 | C6: =CORREL(Dataset!$L$2:$L$121,Dataset!$H$2:$H$121) -> 0.054269915 | D6: =CORREL(Dataset!$L$2:$L$121,Dataset!$I$2:$I$121) -> -0.076226371 | E6: =CORREL(Dataset!$L$2:$L$121,Dataset!$J$2:$J$121) -> -0.053494943 | F6: =CORREL(Dataset!$L$2:$L$121,Dataset!$L$2:$L$121) -> 1

Sheet Insights & Recommendations
A1: DECODELABS – DATA ANALYTICS
A2: PROJECT 2: EXPLORATORY DATA ANALYSIS (EDA)
A3: INSIGHTS & RECOMMENDATIONS
A5: No. | B5: Key Observation
A6: 1 | B6: Sports & Fitness generates the highest total sales among the three categories.
A7: 2 | B7: Vadodara records the highest total sales among the six cities in this dataset.
A8: 3 | B8: Aug is the strongest month by total sales.
A9: 4 | B9: Average order sales are ₹17,590.53, while median order sales are ₹10,178.51; the difference indicates that some higher-value orders influence the average.
A10: 5 | B10: IQR analysis identifies 2 potential outlier observations across Sales and Profit. These should be investigated rather than automatically removed.
A11: 6 | B11: Sales and Profit show a strong positive relationship (correlation ≈ 0.93).
A12: 7 | B12: Discount percentage should be monitored because higher discounts can reduce the profit earned from individual orders.
A15: No.
A16: 1 | B16: Recommendation
A17: 2 | B17: Prioritize the strongest-performing category (Sports & Fitness) while improving visibility and offers for the other categories.
A18: 3 | B18: Study the sales drivers in Vadodara and test whether successful practices can be applied to the other cities.
A19: 4 | B19: Review the factors behind the Aug sales peak and evaluate whether similar campaigns or demand patterns can be repeated.
A20: 5 | B20: Investigate high-value outliers individually to distinguish genuine large orders from possible data-entry issues.
B21: Track discount levels alongside profit, not sales alone, before deciding on future promotions.
